{
  "acceptance": {
    "oriented_cubic_residual_excluding_t0_nonzero": true,
    "squared_residual_equals": 0
  },
  "anchor_metrics": {
    "nonzero_rate_excluding_t0": 1.0,
    "robust_nonzero_candidate": true,
    "sign_stability_rate": 0.8
  },
  "claim_id": "THETA-002",
  "expected_output": {
    "oriented_cubic_residual": 4164,
    "oriented_cubic_residual_excluding_t0": 4164,
    "squared_residual": 0
  },
  "input": {
    "ckm_phase": 3,
    "initial_state": [
      0,
      3,
      3,
      0,
      -1,
      3,
      -3,
      12
    ],
    "op_sequence": [
      1,
      2,
      2,
      4,
      1,
      7,
      4,
      6,
      6,
      2,
      1,
      7,
      5,
      3,
      1,
      4,
      5,
      5,
      1,
      3,
      1,
      4,
      7,
      3,
      3,
      2,
      3,
      1,
      2,
      6,
      6,
      3,
      1,
      3,
      2,
      1
    ],
    "transport_period": 3,
    "weak_kick": 11
  },
  "lane": "weak",
  "sample_id": 166,
  "scenario_hash": "27e186da2b974e5cc2d0c1ab79946f77410e889f6bddce838972ab3f5b1844ef",
  "scenario_id": "theta002_replica_weak_02_sample166",
  "schema_version": "theta002_replication_scenario_v1"
}
